mof_circular_105_2020/__init__.py
mof_circular_105_2020/main.py
mof_circular_105_2020/term.py
mof_circular_105_2020-0.5.2.dist-info/METADATA
mof_circular_105_2020-0.5.2.dist-info/WHEEL
mof_circular_105_2020-0.5.2.dist-info/licenses/LICENSE
mof_circular_105_2020-0.5.2.dist-info/RECORD
