Metadata-Version: 2.4
Name: mof-circular-105-2020
Version: 0.5.2
Summary: Implement the Circular 105/2020 from Ministry of Finance
Project-URL: Documentation, https://github.com/thuyetbao/mof-circular-105-2020#README
Project-URL: Issues, https://github.com/thuyetbao/mof-circular-105-2020/issues
Project-URL: Source, https://github.com/thuyetbao/mof-circular-105-2020
Author-email: Bao Truong <trthuyetbao@gmail.com>
License-Expression: MIT
License-File: LICENSE
Keywords: mof-circular-105-2020,python3
Classifier: Development Status :: 5 - Production/Stable
Classifier: Operating System :: OS Independent
Classifier: Programming Language :: Python
Classifier: Programming Language :: Python :: 3
Classifier: Programming Language :: Python :: 3.9
Classifier: Programming Language :: Python :: 3.10
Classifier: Programming Language :: Python :: 3.11
Classifier: Programming Language :: Python :: 3.12
Classifier: Programming Language :: Python :: 3.13
Requires-Python: >=3.9
